proknow/Audit.py
proknow/CustomMetrics.py
proknow/Exceptions.py
proknow/ProKnow.py
proknow/Requestor.py
proknow/Roles.py
proknow/RtvRequestor.py
proknow/ScorecardTemplates.py
proknow/Session.py
proknow/Uploads.py
proknow/Users.py
proknow/Workspaces.py
proknow/__init__.py
proknow/Collections/Collections.py
proknow/Collections/Patients.py
proknow/Collections/Scorecards.py
proknow/Collections/__init__.py
proknow/Patients/Patients.py
proknow/Patients/Scorecards.py
proknow/Patients/Sros.py
proknow/Patients/Studies.py
proknow/Patients/Tasks.py
proknow/Patients/__init__.py
proknow/Patients/Entities/Doses.py
proknow/Patients/Entities/EntityItem.py
proknow/Patients/Entities/EntitySummary.py
proknow/Patients/Entities/ImageSets.py
proknow/Patients/Entities/Plans.py
proknow/Patients/Entities/StructureSets.py
proknow/Patients/Entities/__init__.py
tests/__init__.py
tests/conftest.py
tests/pktestconfig.py
proknow-0.23.0.dist-info/LICENSE
proknow-0.23.0.dist-info/METADATA
proknow-0.23.0.dist-info/WHEEL
proknow-0.23.0.dist-info/top_level.txt
proknow-0.23.0.dist-info/RECORD
