Metadata-Version: 2.1
Name: proknow
Version: 0.23.0
Summary: Python library for the ProKnow API.
Home-page: https://github.com/proknow/proknow-python
Author: ProKnow
Author-email: support@proknow.com
Classifier: Intended Audience :: Developers
Classifier: License :: OSI Approved :: MIT License
Classifier: Operating System :: OS Independent
Classifier: Programming Language :: Python
Classifier: Programming Language :: Python :: 3
Classifier: Topic :: Software Development :: Libraries :: Python Modules
Requires-Python: >=3.11
License-File: LICENSE
Requires-Dist: requests>=2.18.0
